{"code": "P02", "mainBoard": [{"artist": "Rob Alexander", "borderColor": "black", "colorIdentity": ["R"], "colors": [], "convertedManaCost": 0.0, "count": 15, "foreignData": [], "frameVersion": "1997", "hasFoil": false, "hasNonFoil": true, "isFoil": false, "isPaper": true, "isReprint": true, "layout": "normal", "legalities": {"brawl": "Legal", "commander": "Legal", "duel": "Legal", "future": "Legal", "historic": "Legal", "legacy": "Legal", "modern": "Legal", "pauper": "Legal", "penny": "Legal", "pioneer": "Legal", "standard": "Legal", "vintage": "Legal"}, "mcmId": 9921, "mcmMetaId": 2422, "multiverseId": 8406, "name": "Mountain", "number": "160", "originalText": "R", "originalType": "Land", "prices": {"mtgo": {}, "mtgoFoil": {}, "paper": {"2019-11-09": 0.74}, "paperFoil": {}}, "printings": ["10E", "2ED", "3ED", "4BB", "4ED", "5ED", "6ED", "7ED", "8ED", "9ED", "AKH", "ALA", "ANA", "ARC", "ARN", "ATH", "AVR", "BBD", "BFZ", "BRB", "BTD", "C13", "C14", "C15", "C16", "C17", "C18", "C19", "CED", "CEI", "CHK", "CM2", "CMA", "CMD", "CST", "DD1", "DD2", "DDE", "DDG", "DDH", "DDI", "DDJ", "DDK", "DDL", "DDN", "DDP", "DDS", "DDT", "DDU", "DKM", "DOM", "DPA", "DTK", "E01", "ELD", "EVG", "FBB", "FRF", "G17", "GK1", "GK2", "GNT", "GRN", "GS1", "H09", "HOP", "HOU", "ICE", "INV", "ISD", "ITP", "J14", "JVC", "KLD", "KTK", "LEA", "LEB", "LRW", "M10", "M11", "M12", "M13", "M14", "M15", "M19", "M20", "MBS", "ME1", "ME3", "MIR", "MMQ", "MRD", "NPH", "ODY", "ONS", "ORI", "P02", "PAL00", "PAL01", "PAL03", "PAL04", "PAL05", "PAL06", "PAL99", "PALP", "PARL", "PC2", "PCA", "PD2", "PELP", "PF19", "PGPX", "PGRU", "PMPS", "PMPS06", "PMPS07", "PMPS08", "PMPS09", "PMPS10", "PMPS11", "POR", "PPP1", "PRM", "PRW2", "PRWK", "PS11", "PSAL", "PSS2", "PSS3", "PTC", "PTK", "PZ2", "RAV", "RIX", "RNA", "ROE", "RQS", "RTR", "S99", "SHM", "SOI", "SOM", "SUM", "TD0", "THS", "TMP", "TPR", "TSP", "UGL", "UNH", "USG", "UST", "WAR", "WC00", "WC01", "WC02", "WC03", "WC97", "WC98", "WC99", "XLN", "ZEN"], "purchaseUrls": {"cardmarket": "https://mtgjson.com/links/6497036c707c553f", "tcgplayer": "https://mtgjson.com/links/f57e5cb1f4532c00"}, "rarity": "common", "rulings": [], "scryfallId": "bdfbb15a-d7f4-470a-9d36-78c710a6d397", "scryfallIllustrationId": "3fca7031-9b20-4421-81c7-eb6d21c1b343", "scryfallOracleId": "a3fb7228-e76b-4e96-a40e-20b5fed75685", "subtypes": ["Mountain"], "supertypes": ["Basic"], "tcgplayerProductId": 169, "text": "({T}: Add {R}.)", "type": "Basic Land — Mountain", "types": ["Land"], "uuid": "2add2b17-27ad-5aa7-896c-6806b32c7a9b", "variations": ["cf8e33f1-1b21-5913-96aa-07789dbd3b55", "5737113b-d0ed-5ea1-a947-6b533d863341"]}, {"artist": "DiTerlizzi", "borderColor": "black", "colorIdentity": ["R"], "colors": ["R"], "convertedManaCost": 3.0, "count": 2, "edhrecRank": 19109, "flavorText": "They get along so well with their goats because they're practically goats themselves.", "foreignData": [{"language": "German", "name": "Berittene Goblins", "type": "Beschwörung von Goblins"}, {"language": "Spanish", "name": "Caballeros trasgo"}, {"language": "French", "name": "Cavaliers gobelins"}, {"language": "Italian", "name": "Cavalleggeri Goblin"}, {"language": "Japanese", "name": "ゴブリンの騎兵隊"}], "frameVersion": "1997", "hasFoil": false, "hasNonFoil": true, "isFoil": false, "isPaper": true, "layout": "normal", "legalities": {"commander": "Legal", "duel": "Legal", "legacy": "Legal", "pauper": "Legal", "penny": "Legal", "vintage": "Legal"}, "manaCost": "{2}{R}", "mcmId": 9915, "mcmMetaId": 2386, "multiverseId": 6587, "name": "Goblin Cavaliers", "number": "95", "originalType": "Creature - Goblins", "power": "3", "prices": {"mtgo": {}, "mtgoFoil": {}, "paper": {"2019-11-09": 0.21}, "paperFoil": {}}, "printings": ["ME4", "P02", "S99"], "purchaseUrls": {"cardmarket": "https://mtgjson.com/links/13e4bb1dcd5d6b93", "tcgplayer": "https://mtgjson.com/links/d6a4031733610bb0"}, "rarity": "common", "rulings": [], "scryfallId": "edc6ea02-0642-4fc5-b50c-543dc393bfdd", "scryfallIllustrationId": "d22b258e-3bad-4826-9435-dfc432f0474a", "scryfallOracleId": "be77e3f8-76a3-4d03-a8be-ad4b0b72f929", "subtypes": ["Goblin"], "supertypes": [], "tcgplayerProductId": 138, "toughness": "2", "type": "Creature — Goblin", "types": ["Creature"], "uuid": "b7fea8f7-eb79-5319-aafc-f38f29bf5247"}, {"artist": "Keith Parkinson", "borderColor": "black", "colorIdentity": ["R"], "colors": ["R"], "convertedManaCost": 1.0, "count": 2, "edhrecRank": 16275, "foreignData": [{"language": "German", "name": "Zündelnder Goblin", "text": "Du kannst den Zündelnden Goblin in Deinem Zug vor Deinem Angriff zerstören, damit er einer Kreatur oder einem Spieler Deiner Wahl 1 Schadenspunkt zufügt.", "type": "Beschwörung eines Goblins"}, {"language": "Spanish", "name": "Incendiario trasgo"}, {"language": "French", "name": "Boutefeu gobelin"}, {"language": "Italian", "name": "Goblin Incendiario"}, {"language": "Japanese", "name": "ゴブリンの火つけ役"}], "frameVersion": "1997", "hasFoil": false, "hasNonFoil": true, "isFoil": false, "isPaper": true, "layout": "normal", "legalities": {"commander": "Legal", "duel": "Legal", "legacy": "Legal", "pauper": "Legal", "penny": "Legal", "vintage": "Legal"}, "manaCost": "{R}", "mcmId": 9916, "mcmMetaId": 2399, "multiverseId": 6598, "name": "Goblin Firestarter", "number": "96", "originalText": "On your turn, before you attack, you may destroy Goblin Firestarter to have it deal 1 damage to any one creature or player.", "originalType": "Creature - Goblin", "power": "1", "prices": {"mtgo": {}, "mtgoFoil": {}, "paper": {"2019-11-09": 0.68}, "paperFoil": {}}, "printings": ["ME4", "P02"], "purchaseUrls": {"cardmarket": "https://mtgjson.com/links/9247c2dd467ca1dd", "tcgplayer": "https://mtgjson.com/links/8d27ba37c5d81010"}, "rarity": "uncommon", "rulings": [{"date": "2013-09-20", "text": "If a turn has multiple combat phases, the ability can only be activated before the beginning of the declare attackers step of the first combat phase in that turn."}], "scryfallId": "84ee21ef-26c0-4def-9046-5d6fcfa3bfeb", "scryfallIllustrationId": "59c3a414-4b89-40fa-9661-160a49b96b84", "scryfallOracleId": "18279733-5568-427c-b0a2-044bca28f688", "subtypes": ["Goblin"], "supertypes": [], "tcgplayerProductId": 139, "text": "Sacrifice Goblin Firestarter: It deals 1 damage to any target. Activate this ability only during your turn, before attackers are declared.", "toughness": "1", "type": "Creature — Goblin", "types": ["Creature"], "uuid": "c7324d3c-3847-5fe2-8743-4a9ad6badd76"}, {"artist": "Keith Parkinson", "borderColor": "black", "colorIdentity": ["R"], "colors": ["R"], "convertedManaCost": 3.0, "count": 1, "edhrecRank": 8105, "flavorText": "Lead, follow, or run around like crazy.", "foreignData": [{"language": "German", "name": "Goblin-General", "text": "Wenn der Goblin-General angreift, erhalten alle Deine Goblins +1/+1 bis zum Ende des Zuges.", "type": "Beschwörung eines Goblins"}, {"language": "Spanish", "name": "General trasgo"}, {"language": "French", "name": "Général gobelin"}, {"language": "Italian", "name": "Generale dei Goblin"}, {"language": "Japanese", "name": "ゴブリンの将軍"}], "frameVersion": "1997", "hasFoil": false, "hasNonFoil": true, "isFoil": false, "isPaper": true, "layout": "normal", "legalities": {"commander": "Legal", "duel": "Legal", "legacy": "Legal", "pauper": "Legal", "penny": "Legal", "vintage": "Legal"}, "manaCost": "{1}{R}{R}", "mcmId": 9917, "mcmMetaId": 2403, "multiverseId": 6604, "name": "Goblin General", "number": "97", "originalText": "When Goblin General attacks, all your Goblins get +1/+1 until the end of the turn.", "originalType": "Creature - Goblin", "power": "1", "prices": {"mtgo": {}, "mtgoFoil": {}, "paper": {"2019-11-09": 5.44}, "paperFoil": {}}, "printings": ["ME4", "P02", "S99", "VMA"], "purchaseUrls": {"cardmarket": "https://mtgjson.com/links/153b3bba7575023e", "tcgplayer": "https://mtgjson.com/links/dbae772db29058a8"}, "rarity": "rare", "rulings": [], "scryfallId": "7fdce2e5-60dd-4993-b74c-f49f013b28f0", "scryfallIllustrationId": "c3cec28b-926a-4ddc-ac13-d8d1857eb66d", "scryfallOracleId": "5fab0d9c-ccf7-4c6a-94b4-959be139dad8", "subtypes": ["Goblin", "Warrior"], "supertypes": [], "tcgplayerProductId": 140, "text": "Whenever Goblin General attacks, Goblin creatures you control get +1/+1 until end of turn.", "toughness": "1", "type": "Creature — Goblin Warrior", "types": ["Creature"], "uuid": "16dca3d8-7c40-5a8f-b9a1-85fbf83191f1"}, {"artist": "Pete Venters", "borderColor": "black", "colorIdentity": ["R"], "colors": ["R"], "convertedManaCost": 2.0, "count": 2, "edhrecRank": 14197, "flavorText": "The goblins call the gliders \"death from above.\" Everyone else calls them \"clods in the clouds.\"", "foreignData": [{"language": "German", "name": "Goblinsegler", "text": "Fliegend\nDer Goblinsegler kann nicht blocken.", "type": "Beschwörung eines Goblins"}, {"language": "Spanish", "name": "Planeador trasgo"}, {"language": "French", "name": "Planeur gobelin"}, {"language": "Italian", "name": "Aliante Goblin"}, {"language": "Japanese", "name": "ゴブリンの滑空者"}, {"language": "Portuguese (Brazil)", "name": "Planador dos Goblins"}], "frameVersion": "1997", "hasFoil": false, "hasNonFoil": true, "isFoil": false, "isPaper": true, "layout": "normal", "legalities": {"commander": "Legal", "duel": "Legal", "legacy": "Legal", "modern": "Legal", "pauper": "Legal", "penny": "Legal", "vintage": "Legal"}, "manaCost": "{1}{R}", "mcmId": 9918, "mcmMetaId": 2404, "multiverseId": 6584, "name": "Goblin Glider", "number": "98", "originalText": "Flying\nGoblin Glider can't block.", "originalType": "Creature - Goblin", "power": "1", "prices": {"mtgo": {}, "mtgoFoil": {}, "paper": {"2019-11-09": 0.16}, "paperFoil": {}}, "printings": ["7ED", "8ED", "P02", "S99"], "purchaseUrls": {"cardmarket": "https://mtgjson.com/links/9cb93fa3c2705949", "tcgplayer": "https://mtgjson.com/links/2c7d5490e6050836"}, "rarity": "common", "rulings": [], "scryfallId": "9c29491b-dec1-429d-9950-062582f8164f", "scryfallIllustrationId": "4ad82ded-c6e7-4f6c-afd4-10728d100d97", "scryfallOracleId": "72bce821-46f0-40eb-abdb-575d4305b8fd", "subtypes": ["Goblin"], "supertypes": [], "tcgplayerProductId": 141, "text": "Flying\nGoblin Glider can't block.", "toughness": "1", "type": "Creature — Goblin", "types": ["Creature"], "uuid": "66bcd041-bdb6-5cb9-81aa-6f376d0db425"}, {"artist": "Daniel Gelon", "borderColor": "black", "colorIdentity": ["R"], "colors": ["R"], "convertedManaCost": 3.0, "count": 2, "edhrecRank": 1283, "foreignData": [{"language": "German", "name": "Goblinmatrone", "text": "Wenn die Goblinmatrone aus Deiner Hand ins Spiel kommt, durchsuche Deine Bibliothek nach einer Goblinkarte und nimm die Karte auf Deine Hand. Mische Deine Bibliothek danach neu.", "type": "Beschwörung eines Goblins"}, {"language": "Spanish", "name": "Matrona trasgo"}, {"language": "French", "name": "Matrone gobeline"}, {"language": "Italian", "name": "Matrona Goblin"}, {"language": "Japanese", "name": "ゴブリンの女看守"}, {"language": "Portuguese (Brazil)", "name": "Matrona Goblin"}], "frameVersion": "1997", "hasFoil": false, "hasNonFoil": true, "isFoil": false, "isPaper": true, "layout": "normal", "legalities": {"commander": "Legal", "duel": "Legal", "legacy": "Legal", "modern": "Legal", "pauper": "Legal", "penny": "Legal", "vintage": "Legal"}, "manaCost": "{2}{R}", "mcmId": 9920, "mcmMetaId": 2420, "multiverseId": 6596, "name": "Goblin Matron", "number": "100", "originalText": "When Goblin Matron comes into play from your hand, search your library for a Goblin card and put that card into your hand. Shuffle your library afterwards.", "originalType": "Creature - Goblin", "power": "1", "prices": {"mtgo": {}, "mtgoFoil": {}, "paper": {"2019-11-09": 1.45}, "paperFoil": {}}, "printings": ["7ED", "ATH", "DD1", "EVG", "MH1", "P02", "USG", "VMA"], "purchaseUrls": {"cardmarket": "https://mtgjson.com/links/4b3b30d67a8ba672", "tcgplayer": "https://mtgjson.com/links/d6f0c71ef0c88e45"}, "rarity": "uncommon", "rulings": [{"date": "2004-10-04", "text": "Because the “search” requires you to find a card with certain characteristics, you don’t have to find the card if you don’t want to."}, {"date": "2019-06-14", "text": "If an effect refers to a “[subtype] spell” or “[subtype] card,” it refers only to a spell or card that has that subtype. For example, Goblin War Party is a card that references and creates Goblins, but it isn’t a Goblin card."}], "scryfallId": "f99dc21c-8600-49bf-b0a3-c981f7ec7ac3", "scryfallIllustrationId": "2e7f3874-acb1-4bb6-b104-d22ec2abf0a8", "scryfallOracleId": "145737a7-c597-4dec-b752-207c2d0501e3", "subtypes": ["Goblin"], "supertypes": [], "tcgplayerProductId": 143, "text": "When Goblin Matron enters the battlefield, you may search your library for a Goblin card, reveal that card, put it into your hand, then shuffle your library.", "toughness": "1", "type": "Creature — Goblin", "types": ["Creature"], "uuid": "82e67dc9-5b07-5c1a-9cf4-ecd3616fbf06"}, {"artist": "DiTerlizzi", "borderColor": "black", "colorIdentity": ["R"], "colors": ["R"], "convertedManaCost": 2.0, "count": 2, "edhrecRank": 15680, "flavorText": "Once he'd worked out which end of the thing was sharp, he was promoted to guard duty.", "foreignData": [{"language": "German", "name": "Goblin-Lanzenträger", "type": "Beschwörung eines Goblins"}, {"language": "Spanish", "name": "Lancero trasgo"}, {"language": "French", "name": "Piquier gobelin"}, {"language": "Italian", "name": "Picchiere Goblin"}, {"language": "Japanese", "name": "ゴブリンの長槍使い"}], "frameVersion": "1997", "hasFoil": false, "hasNonFoil": true, "isFoil": false, "isPaper": true, "layout": "normal", "legalities": {"commander": "Legal", "duel": "Legal", "legacy": "Legal", "modern": "Legal", "pauper": "Legal", "penny": "Legal", "vintage": "Legal"}, "manaCost": "{1}{R}", "mcmId": 9922, "mcmMetaId": 2426, "multiverseId": 6582, "name": "Goblin Piker", "number": "102", "originalType": "Creature - Goblin", "power": "2", "prices": {"mtgo": {}, "mtgoFoil": {}, "paper": {"2019-11-09": 0.14}, "paperFoil": {}}, "printings": ["10E", "9ED", "DPA", "M10", "M11", "M12", "P02", "PS11"], "purchaseUrls": {"cardmarket": "https://mtgjson.com/links/83884f33b8f69fd7", "tcgplayer": "https://mtgjson.com/links/be47addbcb8f6056"}, "rarity": "common", "rulings": [], "scryfallId": "2786834d-dbda-40ce-82a4-e518cd554312", "scryfallIllustrationId": "71c18550-7b9e-4974-94a7-73f32a279f23", "scryfallOracleId": "50608184-90d3-43d2-a221-deb186c78323", "subtypes": ["Goblin", "Warrior"], "supertypes": [], "tcgplayerProductId": 145, "toughness": "1", "type": "Creature — Goblin Warrior", "types": ["Creature"], "uuid": "89a22068-8b9f-557a-b430-416825cc5ddd"}, {"artist": "Matt Stawicki", "borderColor": "black", "colorIdentity": ["R"], "colors": ["R"], "convertedManaCost": 2.0, "count": 2, "edhrecRank": 15417, "flavorText": "\"I seen lots o' fights. To win ya gotta bash hard and not get bashed back.\" —Goblin grunt", "foreignData": [{"language": "German", "name": "Goblinbandit", "text": "Der Goblinbandit kann nicht blocken.", "type": "Beschwörung eines Goblins"}, {"language": "Spanish", "name": "Incursor trasgo"}, {"language": "French", "name": "Pillard gobelin"}, {"language": "Italian", "name": "Predone Goblin"}, {"language": "Japanese", "name": "ゴブリンの略奪者"}, {"language": "Portuguese (Brazil)", "name": "Goblin Salteador"}], "frameVersion": "1997", "hasFoil": false, "hasNonFoil": true, "isFoil": false, "isPaper": true, "layout": "normal", "legalities": {"commander": "Legal", "duel": "Legal", "legacy": "Legal", "modern": "Legal", "pauper": "Legal", "penny": "Legal", "vintage": "Legal"}, "manaCost": "{1}{R}", "mcmId": 9923, "mcmMetaId": 2430, "multiverseId": 6583, "name": "Goblin Raider", "number": "103", "originalText": "Goblin Raider can't block.", "originalType": "Creature - Goblin", "power": "2", "prices": {"mtgo": {}, "mtgoFoil": {}, "paper": {"2019-11-09": 0.07}, "paperFoil": {}}, "printings": ["7ED", "8ED", "9ED", "P02", "USG"], "purchaseUrls": {"cardmarket": "https://mtgjson.com/links/d4aba9772a12d463", "tcgplayer": "https://mtgjson.com/links/0a5b046d07f6f971"}, "rarity": "common", "rulings": [], "scryfallId": "68fe9691-d788-42cb-8d13-005724939b62", "scryfallIllustrationId": "a3d9ebed-258c-435f-b6cc-1f553d2e51b7", "scryfallOracleId": "7f11c830-fced-40db-8c02-b3c54f3e4372", "subtypes": ["Goblin", "Warrior"], "supertypes": [], "tcgplayerProductId": 146, "text": "Goblin Raider can't block.", "toughness": "2", "type": "Creature — Goblin Warrior", "types": ["Creature"], "uuid": "c1ce12b2-416a-55fa-b90a-f0bb32083907"}, {"artist": "Jeff Miracola", "borderColor": "black", "colorIdentity": ["R"], "colors": ["R"], "convertedManaCost": 1.0, "count": 3, "edhrecRank": 8173, "flavorText": "He raged at the world, at his family, at his life. But mostly he just raged.", "foreignData": [{"language": "German", "name": "Wütender Goblin", "text": "Für den Wütende Goblin gilt die Einsatzverzögerung nicht", "type": "Beschwörung eines Goblins"}, {"language": "Spanish", "name": "Trasgo furioso"}, {"language": "French", "name": "Gobelin enragé"}, {"language": "Italian", "name": "Goblin Furioso"}, {"language": "Japanese", "name": "怒り狂うゴブリン"}, {"language": "Portuguese (Brazil)", "name": "Goblin Enfurecido"}], "frameVersion": "1997", "hasFoil": false, "hasNonFoil": true, "isFoil": false, "isPaper": true, "isReprint": true, "layout": "normal", "legalities": {"commander": "Legal", "duel": "Legal", "historic": "Legal", "legacy": "Legal", "modern": "Legal", "pauper": "Legal", "penny": "Legal", "vintage": "Legal"}, "manaCost": "{R}", "mcmId": 9934, "mcmMetaId": 4466, "multiverseId": 6581, "name": "Raging Goblin", "number": "114", "originalText": "Raging Goblin is unaffected by summoning sickness.", "originalType": "Creature - Goblin", "power": "1", "prices": {"mtgo": {}, "mtgoFoil": {}, "paper": {"2019-11-09": 0.23}, "paperFoil": {}}, "printings": ["10E", "6ED", "7ED", "8ED", "9ED", "ANA", "ATH", "BRB", "BTD", "DD1", "EVG", "EXO", "M10", "P02", "POR", "PSAL", "S99"], "purchaseUrls": {"cardmarket": "https://mtgjson.com/links/4b47f53443db536d", "tcgplayer": "https://mtgjson.com/links/1dfacb2ea5a03e0a"}, "rarity": "common", "rulings": [], "scryfallId": "e6df5a36-7bd4-4456-a462-54f65089826c", "scryfallIllustrationId": "3f27a894-9e5c-46a7-a433-94f0f3029541", "scryfallOracleId": "30997b43-fc13-41d3-8064-1ccc2cb6fd2b", "subtypes": ["Goblin", "Berserker"], "supertypes": [], "tcgplayerProductId": 195, "text": "Haste (This creature can attack and {T} as soon as it comes under your control.)", "toughness": "1", "type": "Creature — Goblin Berserker", "types": ["Creature"], "uuid": "acdb7b20-d01d-5880-bdc1-f522087d74ad"}, {"artist": "David A. Cherry", "borderColor": "black", "colorIdentity": ["R"], "colors": ["R"], "convertedManaCost": 1.0, "count": 2, "edhrecRank": 6149, "flavorText": "\"This isn't what I meant by 'facing the heat of battle!'\" —Jefan, Talas ship captain", "foreignData": [{"language": "German", "name": "Heiße Glut", "text": "Die Heiße Glut fügt einem Spieler oder einer Kreatur Deiner Wahl X Schadenspunkte zu.", "type": "Hexerei"}, {"language": "Spanish", "name": "Llamarada"}, {"language": "French", "name": "Brasier"}, {"language": "Italian", "name": "Fiammata"}, {"language": "Japanese", "name": "猛火"}, {"language": "Portuguese (Brazil)", "name": "Labareda"}], "frameVersion": "1997", "hasFoil": false, "hasNonFoil": true, "isFoil": false, "isPaper": true, "isReprint": true, "layout": "normal", "legalities": {"commander": "Legal", "duel": "Legal", "legacy": "Legal", "modern": "Legal", "penny": "Legal", "vintage": "Legal"}, "manaCost": "{X}{R}", "mcmId": 9911, "mcmMetaId": 566, "multiverseId": 6600, "name": "Blaze", "number": "91", "originalText": "Blaze deals X damage to any one creature or player.", "originalType": "Sorcery", "prices": {"mtgo": {}, "mtgoFoil": {}, "paper": {"2019-11-09": 0.2}, "paperFoil": {}}, "printings": ["10E", "6ED", "7ED", "8ED", "9ED", "BBD", "DPA", "HOP", "P02", "POR", "PS11", "PTK", "WC00"], "purchaseUrls": {"cardmarket": "https://mtgjson.com/links/589084a9b2ce2be8", "tcgplayer": "https://mtgjson.com/links/0fd42b3f73c448b3"}, "rarity": "uncommon", "rulings": [], "scryfallId": "3940d0ca-0ca2-4446-9330-a554c3e89824", "scryfallIllustrationId": "9c1faa49-4d2e-480e-80f8-57a853ff7835", "scryfallOracleId": "0596920f-9946-42f4-a03b-24aab67f9f1b", "subtypes": [], "supertypes": [], "tcgplayerProductId": 109, "text": "Blaze deals X damage to any target.", "type": "Sorcery", "types": ["Sorcery"], "uuid": "c977e9d9-d782-536c-85a7-f65658e4c63f"}, {"artist": "Michael Weaver", "borderColor": "black", "colorIdentity": ["R"], "colors": ["R"], "convertedManaCost": 1.0, "count": 2, "edhrecRank": 2901, "foreignData": [{"language": "German", "name": "Anschlag der Goblins", "text": "Der Anschlag der Goblins fügt Deinem Gegner Schadenspunkte in Höhe der Anzahl der Goblinkarten, die Du im Spiel hast, zu (das gilt für getappte und ungetappte Goblins).", "type": "Hexerei"}, {"language": "Spanish", "name": "Ataque de guerra trasgo"}, {"language": "French", "name": "Frappe guerrière des gobelins"}, {"language": "Italian", "name": "Offensiva dei Goblin"}, {"language": "Japanese", "name": "ゴブリンの集中攻撃"}], "frameVersion": "1997", "hasFoil": false, "hasNonFoil": true, "isFoil": false, "isPaper": true, "layout": "normal", "legalities": {"commander": "Legal", "duel": "Legal", "legacy": "Legal", "pauper": "Legal", "vintage": "Legal"}, "manaCost": "{R}", "mcmId": 9925, "mcmMetaId": 2457, "multiverseId": 6594, "name": "Goblin War Strike", "number": "105", "originalText": "Goblin War Strike deals to your opponent damage equal to the number of Goblin cards you have in play. (This includes both tapped and untapped Goblin cards.)", "originalType": "Sorcery", "prices": {"mtgo": {}, "mtgoFoil": {}, "paper": {"2019-11-09": 2.13}, "paperFoil": {}}, "printings": ["P02", "SCG"], "purchaseUrls": {"cardmarket": "https://mtgjson.com/links/e10c4385ee5e1db8", "tcgplayer": "https://mtgjson.com/links/ec2e990b934dde55"}, "rarity": "common", "rulings": [], "scryfallId": "738fecfd-1119-4dcb-acd6-ec9715d9c074", "scryfallIllustrationId": "3767c37e-68ba-4f4f-9d5b-9c53cccaa217", "scryfallOracleId": "5944d5c7-65ab-425f-a453-ed5871ca3d73", "subtypes": [], "supertypes": [], "tcgplayerProductId": 148, "text": "Goblin War Strike deals damage to target player or planeswalker equal to the number of Goblins you control.", "type": "Sorcery", "types": ["Sorcery"], "uuid": "1c4dee34-885c-5ef1-9ba0-22f7c610d40a"}, {"artist": "Tom Wänerstrand", "borderColor": "black", "colorIdentity": ["R"], "colors": ["R"], "convertedManaCost": 4.0, "count": 1, "edhrecRank": 1334, "foreignData": [{"language": "German", "name": "Unnachgiebiger Ansturm", "text": "Entappe alle Kreaturen, die in diesem Zug angegriffen haben. Du kannst in diesem Zug einen zusätzlichen Angriff deklarieren.", "type": "Hexerei"}, {"language": "Spanish", "name": "Asalto implacable"}, {"language": "French", "name": "Assaut implacable"}, {"language": "Italian", "name": "Assalto Implacabile"}, {"language": "Japanese", "name": "連続突撃"}, {"language": "Portuguese (Brazil)", "name": "Assalto Implacável"}], "frameVersion": "1997", "hasFoil": false, "hasNonFoil": true, "isFoil": false, "isPaper": true, "isReprint": true, "layout": "normal", "legalities": {"commander": "Legal", "duel": "Legal", "legacy": "Legal", "modern": "Legal", "penny": "Legal", "vintage": "Legal"}, "manaCost": "{2}{R}{R}", "mcmId": 9935, "mcmMetaId": 4612, "multiverseId": 6608, "name": "Relentless Assault", "number": "115", "originalText": "Untap all your creatures that attacked this turn. You may declare an additional attack this turn.", "originalType": "Sorcery", "prices": {"mtgo": {}, "mtgoFoil": {}, "paper": {"2019-11-09": 1.2}, "paperFoil": {}}, "printings": ["10E", "6ED", "7ED", "8ED", "9ED", "DDT", "HOP", "P02", "PTK", "S99", "VIS"], "purchaseUrls": {"cardmarket": "https://mtgjson.com/links/14d72d8606904760", "tcgplayer": "https://mtgjson.com/links/c17edaae86e4016a"}, "rarity": "rare", "rulings": [{"date": "2004-10-04", "text": "If you manage to cast this during a main phase of your opponent’s turn, that opponent’s creatures will untap and that opponent will be able to attack again. It will not allow you to attack during their turn."}, {"date": "2004-10-04", "text": "Abilities that trigger when a creature attacks, blocks, or is blocked will trigger during each combat that turn. Thus, a creature with Rampage will get the bonus added during each attack."}, {"date": "2004-10-04", "text": "A creature that must attack each turn, must only attack once that turn. It is not forced into each attack that turn."}, {"date": "2004-10-04", "text": "It only creates an additional combat and main phase if it resolves during a main phase."}], "scryfallId": "c641c3d6-0364-4209-b908-1717e5e612ad", "scryfallIllustrationId": "f4ecc4bd-780a-4dcc-bf76-1fb778c3d4b5", "scryfallOracleId": "dc1c0e8c-d0c1-445c-968f-7dec91e5d5fc", "subtypes": [], "supertypes": [], "tcgplayerProductId": 202, "text": "Untap all creatures that attacked this turn. After this main phase, there is an additional combat phase followed by an additional main phase.", "type": "Sorcery", "types": ["Sorcery"], "uuid": "8c062364-ca83-5229-b97b-38585318b79c"}, {"artist": "Edward P. Beard, Jr.", "borderColor": "black", "colorIdentity": ["R"], "colors": ["R"], "convertedManaCost": 2.0, "count": 3, "edhrecRank": 9357, "flavorText": "Fire finds its form in the heat of the forge.", "foreignData": [{"language": "German", "name": "Vulkanhammer", "text": "Der Vulkanhammer fügt einer Kreatur oder einem Spieler Deiner Wahl 3 Schadenspunkte zu.", "type": "Hexerei"}, {"language": "Spanish", "name": "Martillo volcanico"}, {"language": "French", "name": "Marteau volcanique"}, {"language": "Italian", "name": "Martello Vulcanico"}, {"language": "Japanese", "name": "火山の鎚"}, {"language": "Portuguese (Brazil)", "name": "Martelo Vulcânico"}], "frameVersion": "1997", "hasFoil": false, "hasNonFoil": true, "isFoil": false, "isPaper": true, "isReprint": true, "layout": "normal", "legalities": {"commander": "Legal", "duel": "Legal", "legacy": "Legal", "modern": "Legal", "pauper": "Legal", "penny": "Legal", "vintage": "Legal"}, "manaCost": "{1}{R}", "mcmId": 9939, "mcmMetaId": 6420, "multiverseId": 6593, "name": "Volcanic Hammer", "number": "119", "originalText": "Volcanic Hammer deals 3 damage to any one creature or player.", "originalType": "Sorcery", "prices": {"mtgo": {}, "mtgoFoil": {}, "paper": {"2019-11-09": 0.24}, "paperFoil": {}}, "printings": ["7ED", "8ED", "9ED", "P02", "PJJT", "POR", "PRM", "PSAL", "PSUS", "S99"], "purchaseUrls": {"cardmarket": "https://mtgjson.com/links/215b68b524b0d5a5", "tcgplayer": "https://mtgjson.com/links/82c01ce15b431d42"}, "rarity": "common", "rulings": [], "scryfallId": "58c0489d-b073-4ad4-b044-447fcc865b6c", "scryfallIllustrationId": "b82b511b-2b1a-4b5c-a1be-ded6d361d2a2", "scryfallOracleId": "98fa5a06-0553-40fd-999c-bc31c9b3f4db", "subtypes": [], "supertypes": [], "tcgplayerProductId": 244, "text": "Volcanic Hammer deals 3 damage to any target.", "type": "Sorcery", "types": ["Sorcery"], "uuid": "8e08bdfa-d07c-5f81-bbd5-42fece6c7174"}, {"artist": "Rob Alexander", "borderColor": "black", "colorIdentity": ["R"], "colors": ["R"], "convertedManaCost": 6.0, "count": 1, "edhrecRank": 2864, "foreignData": [{"language": "German", "name": "Verbrannte Steppe", "text": "Du zerstörst 4 Deiner Länder und Dein Gegner zerstört vier seiner Länder. Die Verbrannte Steppe fügt jeder Kreatur 4 Schadenspunkte zu.", "type": "Hexerei"}, {"language": "Spanish", "name": "Incendio destructivo"}, {"language": "French", "name": "Feu dévastateur"}, {"language": "Italian", "name": "Incendio Selvaggio"}, {"language": "Japanese", "name": "燎原の火"}, {"language": "Portuguese (Brazil)", "name": "Fogo Grego"}], "frameVersion": "1997", "hasFoil": false, "hasNonFoil": true, "isFoil": false, "isPaper": true, "layout": "normal", "legalities": {"commander": "Legal", "duel": "Legal", "legacy": "Legal", "modern": "Legal", "penny": "Legal", "vintage": "Legal"}, "manaCost": "{4}{R}{R}", "mcmId": 9940, "mcmMetaId": 6630, "multiverseId": 6610, "name": "Wildfire", "number": "120", "originalText": "You destroy four of your lands and your opponent destroys four of his or her lands. Then Wildfire deals 4 damage to each creature. (This includes your creatures.)", "originalType": "Sorcery", "prices": {"mtgo": {}, "mtgoFoil": {}, "paper": {"2019-11-09": 0.87}, "paperFoil": {}}, "printings": ["7ED", "9ED", "MM2", "P02", "USG", "WC99"], "purchaseUrls": {"cardmarket": "https://mtgjson.com/links/5fec0ccdd4fdb090", "tcgplayer": "https://mtgjson.com/links/9f484139a27415ae"}, "rarity": "rare", "rulings": [], "scryfallId": "b69cfcb0-db68-4494-a3e1-7c2ca279fcf5", "scryfallIllustrationId": "cc5f3d10-bc15-445c-84f6-073e4ecf261e", "scryfallOracleId": "0da68ca2-07fd-4359-95a9-fb2f815e6ed0", "subtypes": [], "supertypes": [], "tcgplayerProductId": 249, "text": "Each player sacrifices four lands. Wildfire deals 4 damage to each creature.", "type": "Sorcery", "types": ["Sorcery"], "uuid": "bff1292e-5bcb-5061-a80f-b194d3ef3e08"}], "meta": {"date": "2019-11-10", "pricesDate": "2019-11-10", "version": "4.6.0+20191110"}, "name": "Goblin Fire", "releaseDate": "1998-06-24", "sideBoard": [], "type": "Theme Deck"}