{"code": "RQS", "mainBoard": [{"artist": "Christopher Rush", "borderColor": "white", "colorIdentity": ["G"], "colors": [], "convertedManaCost": 0.0, "count": 4, "foreignData": [], "frameVersion": "1993", "hasFoil": false, "hasNonFoil": true, "isFoil": false, "isPaper": true, "isReprint": true, "isStarter": true, "layout": "normal", "legalities": {"brawl": "Legal", "commander": "Legal", "duel": "Legal", "future": "Legal", "historic": "Legal", "legacy": "Legal", "modern": "Legal", "pauper": "Legal", "penny": "Legal", "pioneer": "Legal", "standard": "Legal", "vintage": "Legal"}, "name": "Forest", "number": "63", "printings": ["10E", "2ED", "3ED", "4BB", "4ED", "5ED", "6ED", "7ED", "8ED", "9ED", "AKH", "ALA", "ANA", "ARC", "ATH", "AVR", "BBD", "BFZ", "BRB", "BTD", "C13", "C14", "C15", "C16", "C17", "C18", "C19", "CED", "CEI", "CHK", "CM2", "CMA", "CMD", "CST", "DD1", "DDD", "DDE", "DDG", "DDH", "DDJ", "DDL", "DDM", "DDO", "DDP", "DDR", "DDS", "DDU", "DKM", "DOM", "DPA", "DTK", "E01", "ELD", "EVG", "FBB", "FRF", "G17", "GK1", "GK2", "GNT", "GRN", "GS1", "GVL", "H09", "HOP", "HOU", "ICE", "INV", "ISD", "ITP", "J14", "KLD", "KTK", "LEA", "LEB", "LRW", "M10", "M11", "M12", "M13", "M14", "M15", "M19", "M20", "MBS", "ME1", "ME3", "MIR", "MMQ", "MRD", "NPH", "ODY", "ONS", "ORI", "P02", "PAL00", "PAL01", "PAL03", "PAL04", "PAL05", "PAL06", "PAL99", "PALP", "PARL", "PC2", "PCA", "PELP", "PF19", "PGPX", "PGRU", "PMPS", "PMPS06", "PMPS07", "PMPS08", "PMPS09", "PMPS10", "PMPS11", "POR", "PPP1", "PRM", "PRW2", "PRWK", "PS11", "PSAL", "PSS2", "PSS3", "PTC", "PTK", "PZ2", "RAV", "RIX", "RNA", "ROE", "RQS", "RTR", "S99", "SHM", "SOI", "SOM", "SUM", "TD0", "TD2", "THS", "TMP", "TPR", "TSP", "UGL", "UNH", "USG", "UST", "WAR", "WC00", "WC01", "WC02", "WC03", "WC04", "WC97", "WC98", "WC99", "XLN", "ZEN"], "rarity": "common", "rulings": [], "scryfallId": "3d09a0c7-3934-4bf3-a56a-5b670b168eee", "scryfallIllustrationId": "a65460f1-5185-4bae-94bd-ed49a330d505", "scryfallOracleId": "b34bb2dc-c1af-4d77-b0b3-a0fb342a5fc6", "subtypes": ["Forest"], "supertypes": ["Basic"], "text": "({T}: Add {G}.)", "type": "Basic Land — Forest", "types": ["Land"], "uuid": "b4d56b6a-8c8d-5412-befd-6b95a54ad027", "variations": ["3eb0fcb5-95cc-5a56-b8bd-a486893e653e", "67d6892b-ac25-5bec-8cb4-77514104fe6f"]}, {"artist": "Jesper Myrfors", "borderColor": "white", "colorIdentity": ["W"], "colors": [], "convertedManaCost": 0.0, "count": 4, "foreignData": [], "frameVersion": "1993", "hasFoil": false, "hasNonFoil": true, "isFoil": false, "isPaper": true, "isReprint": true, "isStarter": true, "layout": "normal", "legalities": {"brawl": "Legal", "commander": "Legal", "duel": "Legal", "future": "Legal", "historic": "Legal", "legacy": "Legal", "modern": "Legal", "pauper": "Legal", "penny": "Legal", "pioneer": "Legal", "standard": "Legal", "vintage": "Legal"}, "name": "Plains", "number": "52", "printings": ["10E", "2ED", "3ED", "4BB", "4ED", "5ED", "6ED", "7ED", "8ED", "9ED", "AKH", "ALA", "ANA", "ARC", "ATH", "AVR", "BBD", "BFZ", "BRB", "C13", "C14", "C15", "C16", "C17", "C18", "C19", "CED", "CEI", "CHK", "CM2", "CMA", "CMD", "CST", "DDC", "DDE", "DDF", "DDG", "DDH", "DDI", "DDK", "DDL", "DDN", "DDO", "DDP", "DDQ", "DOM", "DTK", "DVD", "E01", "ELD", "FBB", "FRF", "G17", "GK1", "GK2", "GNT", "GRN", "GS1", "H09", "HOP", "HOU", "ICE", "INV", "ISD", "ITP", "J14", "KLD", "KTK", "LEA", "LEB", "LRW", "M10", "M11", "M12", "M13", "M14", "M15", "M19", "M20", "MBS", "MD1", "ME1", "ME3", "MIR", "MMQ", "MRD", "NPH", "ODY", "ONS", "ORI", "P02", "PAL00", "PAL01", "PAL03", "PAL04", "PAL05", "PAL06", "PAL99", "PALP", "PARL", "PC2", "PCA", "PDGM", "PELP", "PF19", "PGPX", "PGRU", "PMPS", "PMPS06", "PMPS07", "PMPS08", "PMPS09", "PMPS10", "PMPS11", "POR", "PPP1", "PRM", "PRW2", "PRWK", "PS11", "PSAL", "PSS2", "PSS3", "PTC", "PTK", "PZ2", "RAV", "RIX", "RNA", "ROE", "RQS", "RTR", "S99", "SHM", "SOI", "SOM", "SUM", "TD0", "TD2", "THS", "TMP", "TPR", "TSP", "UGL", "UNH", "USG", "UST", "WAR", "WC00", "WC02", "WC03", "WC04", "WC97", "WC98", "XLN", "ZEN"], "rarity": "common", "rulings": [], "scryfallId": "f711d96c-7dad-4045-8008-b4328908c9ee", "scryfallIllustrationId": "5c71d8f0-6361-4936-9886-e4309c5116f9", "scryfallOracleId": "bc71ebf6-2056-41f7-be35-b2e5c34afa99", "subtypes": ["Plains"], "supertypes": ["Basic"], "text": "({T}: Add {W}.)", "type": "Basic Land — Plains", "types": ["Land"], "uuid": "6e3af2c1-ad73-5353-a442-cf3f8d945eb7", "variations": ["03e05138-9827-5311-ad9b-bb4b05f5b5d9", "1ba358d2-b546-5fd7-985d-9e33f33cd18e"]}, {"artist": "Dan Frazier", "borderColor": "white", "colorIdentity": ["B"], "colors": [], "convertedManaCost": 0.0, "count": 4, "foreignData": [], "frameVersion": "1993", "hasFoil": false, "hasNonFoil": true, "isFoil": false, "isPaper": true, "isReprint": true, "isStarter": true, "layout": "normal", "legalities": {"brawl": "Legal", "commander": "Legal", "duel": "Legal", "future": "Legal", "historic": "Legal", "legacy": "Legal", "modern": "Legal", "pauper": "Legal", "penny": "Legal", "pioneer": "Legal", "standard": "Legal", "vintage": "Legal"}, "name": "Swamp", "number": "57", "printings": ["10E", "2ED", "3ED", "4BB", "4ED", "5ED", "6ED", "7ED", "8ED", "9ED", "AKH", "ALA", "ANA", "ARC", "ATH", "AVR", "BBD", "BFZ", "BRB", "BTD", "C13", "C14", "C15", "C16", "C17", "C18", "C19", "CED", "CEI", "CHK", "CM2", "CMA", "CMD", "CST", "DDC", "DDD", "DDE", "DDH", "DDJ", "DDK", "DDM", "DDN", "DDP", "DDQ", "DDR", "DKM", "DOM", "DPA", "DTK", "DVD", "E01", "ELD", "FBB", "FRF", "G17", "GK1", "GK2", "GNT", "GRN", "GVL", "H09", "HOP", "HOU", "ICE", "INV", "ISD", "ITP", "J14", "KLD", "KTK", "LEA", "LEB", "LRW", "M10", "M11", "M12", "M13", "M14", "M15", "M19", "M20", "MBS", "MD1", "ME1", "ME3", "MIR", "MMQ", "MRD", "NPH", "ODY", "ONS", "ORI", "P02", "PAL00", "PAL01", "PAL03", "PAL04", "PAL05", "PAL06", "PAL99", "PALP", "PARL", "PC2", "PCA", "PD3", "PELP", "PF19", "PGPX", "PGRU", "PHUK", "PMPS", "PMPS06", "PMPS07", "PMPS08", "PMPS09", "PMPS10", "PMPS11", "POR", "PPP1", "PRM", "PRW2", "PRWK", "PS11", "PSAL", "PSS2", "PSS3", "PTC", "PTK", "RAV", "RIX", "RNA", "ROE", "RQS", "RTR", "S99", "SHM", "SOI", "SOM", "SUM", "TD0", "TD2", "THS", "TMP", "TPR", "TSP", "UGL", "UNH", "USG", "UST", "WAR", "WC01", "WC02", "WC03", "WC97", "WC98", "WC99", "XLN", "ZEN"], "rarity": "common", "rulings": [], "scryfallId": "38a52061-543a-4b8b-af22-646dc6cd1563", "scryfallIllustrationId": "e329fb85-5db8-4c67-b861-8904ce73e818", "scryfallOracleId": "56719f6a-1a6c-4c0a-8d21-18f7d7350b68", "subtypes": ["Swamp"], "supertypes": ["Basic"], "text": "({T}: Add {B}.)", "type": "Basic Land — Swamp", "types": ["Land"], "uuid": "8dfe5602-d587-5884-a74a-c34464b53931", "variations": ["66345e8d-4bdd-5d76-aadc-3554a0e45ad4", "a151f11f-ae0d-5734-ac56-3c08d30f38cc"]}, {"artist": "Ron Spencer", "borderColor": "white", "colorIdentity": ["B"], "colors": ["B"], "convertedManaCost": 2.0, "count": 2, "edhrecRank": 16820, "flavorText": "On guard for larger dangers, we underestimated the power and speed of the Imp's muck-crusted claws.", "foreignData": [], "frameVersion": "1993", "hasFoil": false, "hasNonFoil": true, "isFoil": false, "isPaper": true, "isReprint": true, "isStarter": true, "layout": "normal", "legalities": {"commander": "Legal", "duel": "Legal", "legacy": "Legal", "modern": "Legal", "oldschool": "Legal", "pauper": "Legal", "penny": "Legal", "vintage": "Legal"}, "manaCost": "{1}{B}", "name": "Bog Imp", "number": "15", "power": "1", "printings": ["4BB", "4ED", "5ED", "6ED", "7ED", "8ED", "9ED", "DRK", "ITP", "POR", "REN", "RQS", "S99"], "rarity": "common", "rulings": [], "scryfallId": "45d8846a-ce2e-4261-908a-29fb1ef7caa1", "scryfallIllustrationId": "43e5d0a8-f162-47ac-ad77-06d1dedc9199", "scryfallOracleId": "45b94e3c-a905-435b-aee5-bec9239fd24c", "subtypes": ["Imp"], "supertypes": [], "text": "Flying (This creature can't be blocked except by creatures with flying or reach.)", "toughness": "1", "type": "Creature — Imp", "types": ["Creature"], "uuid": "d7ae95c2-294b-5e53-8986-55edf12388bd"}, {"artist": "Amy Weber", "borderColor": "white", "colorIdentity": ["G"], "colors": ["G"], "convertedManaCost": 1.0, "count": 2, "edhrecRank": 5377, "flavorText": "The only sound was the gentle clicking of the Faeries' wings. Then those intruders who were still standing turned and fled. One thing was certain: they didn't think the Scryb were very funny anymore.", "foreignData": [], "frameVersion": "1993", "hasFoil": false, "hasNonFoil": true, "isFoil": false, "isPaper": true, "isReprint": true, "isStarter": true, "layout": "normal", "legalities": {"commander": "Legal", "duel": "Legal", "legacy": "Legal", "oldschool": "Legal", "pauper": "Legal", "penny": "Legal", "vintage": "Legal"}, "manaCost": "{G}", "name": "Scryb Sprites", "number": "42", "power": "1", "printings": ["2ED", "3ED", "4BB", "4ED", "5ED", "BRB", "CED", "CEI", "FBB", "ITP", "LEA", "LEB", "ME1", "ME3", "PRM", "RQS", "SUM"], "rarity": "common", "rulings": [], "scryfallId": "dcc83274-b0ae-46f4-8a85-0ad3a3b2921d", "scryfallIllustrationId": "c0050f7c-26f0-4466-aa48-24373f6a3dc9", "scryfallOracleId": "a1f20695-6f08-4d5c-9fba-b0018bee298e", "subtypes": ["Faerie"], "supertypes": [], "text": "Flying", "toughness": "1", "type": "Creature — Faerie", "types": ["Creature"], "uuid": "720e5761-c9fb-560f-81d1-0be04d6aba65"}, {"artist": "Jeff A. Menges", "borderColor": "white", "colorIdentity": ["B"], "colors": ["B"], "convertedManaCost": 4.0, "count": 1, "edhrecRank": 16231, "flavorText": "'Twas in the bogs of Cannelbrae My mate did meet an early grave 'Twas nothing left for us to save In the peat-filled bogs of Cannelbrae.", "foreignData": [], "frameVersion": "1993", "hasFoil": false, "hasNonFoil": true, "isFoil": false, "isPaper": true, "isReprint": true, "isStarter": true, "layout": "normal", "legalities": {"commander": "Legal", "duel": "Legal", "legacy": "Legal", "modern": "Legal", "oldschool": "Legal", "penny": "Legal", "vintage": "Legal"}, "manaCost": "{3}{B}", "name": "Bog Wraith", "number": "16", "power": "3", "printings": ["10E", "2ED", "3ED", "4BB", "4ED", "5ED", "6ED", "7ED", "8ED", "9ED", "CED", "CEI", "FBB", "ITP", "LEA", "LEB", "M10", "POR", "RQS", "S99", "SUM"], "rarity": "uncommon", "rulings": [], "scryfallId": "9a6415bb-3b47-4a44-ad5c-13ecf44ee5af", "scryfallIllustrationId": "e1913715-7061-422a-ae16-2f5b7c939111", "scryfallOracleId": "508248d1-09a4-4e41-a4c9-286618e5061e", "subtypes": ["Wraith"], "supertypes": [], "text": "Swampwalk (This creature can't be blocked as long as defending player controls a Swamp.)", "toughness": "3", "type": "Creature — Wraith", "types": ["Creature"], "uuid": "60f7c2e6-ad0c-5a49-a995-6802824fa7db"}, {"artist": "Mike Kimble", "borderColor": "white", "colorIdentity": ["G"], "colors": ["G"], "convertedManaCost": 5.0, "count": 1, "edhrecRank": 16851, "flavorText": "\"And the unclean spirits went out, and entered the swine: and the herd ran violently . . . .\" —Mark 5:13", "foreignData": [], "frameVersion": "1993", "hasFoil": false, "hasNonFoil": true, "isFoil": false, "isPaper": true, "isReprint": true, "isStarter": true, "layout": "normal", "legalities": {"commander": "Legal", "duel": "Legal", "legacy": "Legal", "oldschool": "Legal", "pauper": "Legal", "vintage": "Legal"}, "manaCost": "{4}{G}", "name": "Durkwood Boars", "number": "38", "power": "4", "printings": ["4BB", "4ED", "5ED", "ITP", "LEG", "REN", "RQS", "S00", "S99"], "rarity": "common", "rulings": [], "scryfallId": "eaa6d256-5f18-40be-bf1f-96fc6703d689", "scryfallIllustrationId": "5bd90ea8-6521-48e9-80d0-4f4b4b5a9489", "scryfallOracleId": "8bb2ac6c-20aa-46dd-883f-b629855cabb0", "subtypes": ["Boar"], "supertypes": [], "toughness": "4", "type": "Creature — Boar", "types": ["Creature"], "uuid": "7d3b0868-aee3-5fbf-9134-d8135201c158"}, {"artist": "Melissa A. Benson", "borderColor": "white", "colorIdentity": ["G"], "colors": ["G"], "convertedManaCost": 5.0, "count": 1, "edhrecRank": 13605, "flavorText": "\"Sometimes it is better to be swift of foot than strong of swordarm.\" —Elven proverb", "foreignData": [], "frameVersion": "1993", "hasFoil": false, "hasNonFoil": true, "isFoil": false, "isPaper": true, "isReprint": true, "isStarter": true, "layout": "normal", "legalities": {"commander": "Legal", "duel": "Legal", "legacy": "Legal", "modern": "Legal", "oldschool": "Legal", "penny": "Legal", "vintage": "Legal"}, "manaCost": "{3}{G}{G}", "name": "Elven Riders", "number": "39", "power": "3", "printings": ["10E", "4BB", "4ED", "5ED", "6ED", "DPA", "ITP", "LEG", "ONS", "PS11", "REN", "RQS"], "rarity": "uncommon", "rulings": [{"date": "2007-05-01", "text": "Creatures with the Reach ability (such as Giant Spider) don’t actually have Flying, so they can’t block this."}], "scryfallId": "e61c271c-d705-4f7a-b9ef-d646eee634d7", "scryfallIllustrationId": "0a8eaf21-c936-4949-9240-d9f7b9101054", "scryfallOracleId": "9a6ff511-3c8f-446e-8cad-b8997a753958", "subtypes": ["Elf"], "supertypes": [], "text": "Elven Riders can't be blocked except by Walls and/or creatures with flying.", "toughness": "3", "type": "Creature — Elf", "types": ["Creature"], "uuid": "ad763284-f5a7-51f3-b75b-ce78a6077d3a"}, {"artist": "Jeff A. Menges", "borderColor": "white", "colorIdentity": ["G"], "colors": ["G"], "convertedManaCost": 2.0, "count": 1, "edhrecRank": 5188, "flavorText": "Don't try to outrun one of Dominia's Grizzlies; it'll catch you, knock you down, and eat you. Of course, you could run up a tree. In that case you'll get a nice view before it knocks the tree down and eats you.", "foreignData": [], "frameVersion": "1993", "hasFoil": false, "hasNonFoil": true, "isFoil": false, "isPaper": true, "isReprint": true, "isStarter": true, "layout": "normal", "legalities": {"commander": "Legal", "duel": "Legal", "legacy": "Legal", "modern": "Legal", "oldschool": "Legal", "pauper": "Legal", "penny": "Legal", "vintage": "Legal"}, "manaCost": "{1}{G}", "name": "Grizzly Bears", "number": "41", "power": "2", "printings": ["10E", "2ED", "3ED", "4BB", "4ED", "5ED", "6ED", "7ED", "8ED", "9ED", "CED", "CEI", "FBB", "ITP", "LEA", "LEB", "POR", "RQS", "S99", "SUM"], "rarity": "common", "rulings": [], "scryfallId": "88bdf144-ac1e-4f3f-9404-38b58c3140c4", "scryfallIllustrationId": "0573828d-f238-4eac-9dce-a0be34cefcb1", "scryfallOracleId": "14c8f55d-d177-4c25-a931-ebeb9e6062a0", "subtypes": ["Bear"], "supertypes": [], "toughness": "2", "type": "Creature — Bear", "types": ["Creature"], "uuid": "edd74a14-1175-5f7c-ac7c-00ce00ace520"}, {"artist": "Cornelius Brudi", "borderColor": "white", "colorIdentity": ["W"], "colors": ["W"], "convertedManaCost": 3.0, "count": 2, "edhrecRank": 17142, "flavorText": "\"'Do you know, I always thought Unicorns were fabulous monsters, too? I never saw one alive before!' 'Well, now that we have seen each other,' said the Unicorn, 'if you'll believe in me, I'll believe in you.'\" —Lewis Carroll", "foreignData": [], "frameVersion": "1993", "hasFoil": false, "hasNonFoil": true, "isFoil": false, "isPaper": true, "isReprint": true, "isStarter": true, "layout": "normal", "legalities": {"commander": "Legal", "duel": "Legal", "legacy": "Legal", "oldschool": "Legal", "pauper": "Legal", "vintage": "Legal"}, "manaCost": "{2}{W}", "name": "Pearled Unicorn", "number": "6", "power": "2", "printings": ["2ED", "3ED", "4BB", "4ED", "5ED", "CED", "CEI", "FBB", "ITP", "LEA", "LEB", "RQS", "SUM"], "rarity": "common", "rulings": [], "scryfallId": "b291c1ae-2a0f-4a11-892a-7aa5c7021b0f", "scryfallIllustrationId": "0125d81d-dc67-4cf9-a684-3cc823ef8421", "scryfallOracleId": "c071be90-0531-40cc-af46-0cbe80c4ddd4", "subtypes": ["Unicorn"], "supertypes": [], "toughness": "2", "type": "Creature — Unicorn", "types": ["Creature"], "uuid": "5708f555-362a-528f-87f8-c6abab5aabfa"}, {"artist": "Harold McNeill", "borderColor": "white", "colorIdentity": ["W"], "colors": ["W"], "convertedManaCost": 2.0, "count": 2, "edhrecRank": 14170, "flavorText": "\"Healing is a matter of time, but it is sometimes also a matter of opportunity.\" —D'Avenant proverb", "foreignData": [], "frameVersion": "1993", "hasFoil": false, "hasNonFoil": true, "isFoil": false, "isPaper": true, "isReprint": true, "isStarter": true, "layout": "normal", "legalities": {"commander": "Legal", "duel": "Legal", "legacy": "Legal", "oldschool": "Legal", "pauper": "Legal", "vintage": "Legal"}, "manaCost": "{X}{W}{W}", "name": "Alabaster Potion", "number": "1", "printings": ["4BB", "4ED", "5ED", "ITP", "LEG", "ME3", "REN", "RQS"], "rarity": "common", "rulings": [], "scryfallId": "bb38b274-805c-41a3-8cba-c78e03d5dcd9", "scryfallIllustrationId": "932e07e8-c01b-45cb-ae4c-0a7b0725ea2f", "scryfallOracleId": "2fcca686-03c8-4407-9f9f-2b7462470044", "subtypes": [], "supertypes": [], "text": "Choose one —\n• Target player gains X life.\n• Prevent the next X damage that would be dealt to any target this turn.", "type": "Instant", "types": ["Instant"], "uuid": "4e0b2750-be8a-5ab8-a416-24422650302d"}, {"artist": "Dan Frazier", "borderColor": "white", "colorIdentity": ["W"], "colors": ["W"], "convertedManaCost": 1.0, "count": 2, "edhrecRank": 13147, "foreignData": [], "frameVersion": "1993", "hasFoil": false, "hasNonFoil": true, "isFoil": false, "isPaper": true, "isReprint": true, "isStarter": true, "layout": "normal", "legalities": {"commander": "Legal", "duel": "Legal", "legacy": "Legal", "modern": "Legal", "oldschool": "Legal", "pauper": "Legal", "penny": "Legal", "vintage": "Legal"}, "manaCost": "{W}", "name": "Healing Salve", "number": "4", "printings": ["2ED", "3ED", "4BB", "4ED", "5ED", "6ED", "7ED", "8ED", "BRB", "CED", "CEI", "DDC", "DVD", "FBB", "ITP", "LEA", "LEB", "ME4", "MIR", "RQS", "SUM", "USG"], "rarity": "common", "rulings": [], "scryfallId": "cd7e6bd1-6866-46e5-9c74-c4d72b8e491d", "scryfallIllustrationId": "a73aefac-02c1-4a79-b1fc-9aceebbe432b", "scryfallOracleId": "8da8644c-75a1-4fe9-8e94-900d948d631c", "subtypes": [], "supertypes": [], "text": "Choose one —\n• Target player gains 3 life.\n• Prevent the next 3 damage that would be dealt to any target this turn.", "type": "Instant", "types": ["Instant"], "uuid": "9abc293e-1637-56b0-a6d9-04e54e006012"}, {"artist": "Ron Spencer", "borderColor": "white", "colorIdentity": ["B"], "colors": ["B"], "convertedManaCost": 2.0, "count": 2, "edhrecRank": 5253, "foreignData": [], "frameVersion": "1993", "hasFoil": false, "hasNonFoil": true, "isFoil": false, "isPaper": true, "isReprint": true, "isStarter": true, "layout": "normal", "legalities": {"commander": "Legal", "duel": "Legal", "legacy": "Legal", "modern": "Legal", "oldschool": "Legal", "pauper": "Legal", "penny": "Legal", "vintage": "Legal"}, "manaCost": "{1}{B}", "name": "Terror", "number": "24", "printings": ["10E", "2ED", "3ED", "4BB", "4ED", "5ED", "6ED", "ATH", "BRB", "BTD", "CED", "CEI", "DPA", "FBB", "FNM", "ITP", "LEA", "LEB", "ME4", "MRD", "P05", "PRM", "PS11", "RQS", "SUM", "TD0"], "rarity": "common", "rulings": [], "scryfallId": "15828ee1-1d6e-4da4-9090-f3b0ee756a21", "scryfallIllustrationId": "f868fd9b-79d8-4269-b13d-3b41bc586895", "scryfallOracleId": "b81f041d-98db-4408-9472-c483e4a502bc", "subtypes": [], "supertypes": [], "text": "Destroy target nonartifact, nonblack creature. It can't be regenerated.", "type": "Instant", "types": ["Instant"], "uuid": "a817e22b-c5ae-54f2-abb1-06f697ab17e3"}, {"artist": "Jeff A. Menges", "borderColor": "white", "colorIdentity": ["B"], "colors": ["B"], "convertedManaCost": 1.0, "count": 1, "edhrecRank": 6030, "foreignData": [], "frameVersion": "1993", "hasFoil": false, "hasNonFoil": true, "isFoil": false, "isPaper": true, "isReprint": true, "isStarter": true, "layout": "normal", "legalities": {"commander": "Legal", "duel": "Legal", "legacy": "Legal", "modern": "Legal", "oldschool": "Legal", "pauper": "Legal", "penny": "Legal", "pioneer": "Legal", "vintage": "Legal"}, "manaCost": "{B}", "name": "Raise Dead", "number": "21", "printings": ["2ED", "3ED", "4BB", "4ED", "5ED", "6ED", "7ED", "8ED", "9ED", "CED", "CEI", "CN2", "FBB", "ITP", "LEA", "LEB", "P02", "POR", "RQS", "S99", "SUM", "W17"], "rarity": "common", "rulings": [{"date": "2004-10-04", "text": "You must show the card you bring out of the graveyard to your opponent."}, {"date": "2004-10-04", "text": "The creature being brought back is chosen on announcement and not on resolution of the spell because it is targeted."}], "scryfallId": "843ad013-9342-4a59-8a3d-be69f25ca081", "scryfallIllustrationId": "f322bbca-db60-4733-9d6d-8c83921687a5", "scryfallOracleId": "cbc9c731-181a-4f00-a7b0-eb7e56eac2ea", "subtypes": [], "supertypes": [], "text": "Return target creature card from your graveyard to your hand.", "type": "Sorcery", "types": ["Sorcery"], "uuid": "626eb7f4-f387-5d60-867f-0495141b30f3"}, {"artist": "NéNé Thomas", "borderColor": "white", "colorIdentity": ["G"], "colors": ["G"], "convertedManaCost": 3.0, "count": 1, "edhrecRank": 8264, "foreignData": [], "frameVersion": "1993", "hasFoil": false, "hasNonFoil": true, "isFoil": false, "isPaper": true, "isReprint": true, "isStarter": true, "layout": "normal", "legalities": {"commander": "Legal", "duel": "Legal", "legacy": "Legal", "oldschool": "Legal", "penny": "Legal", "vintage": "Legal"}, "manaCost": "{2}{G}", "name": "Untamed Wilds", "number": "43", "printings": ["4BB", "4ED", "5ED", "6ED", "7ED", "ITP", "LEG", "P02", "POR", "REN", "RQS", "S99"], "rarity": "uncommon", "rulings": [{"date": "2004-10-04", "text": "Because the “search” requires you to find a card with certain characteristics, you don’t have to find the card if you don’t want to."}, {"date": "2006-10-15", "text": "Can fetch a snow land."}], "scryfallId": "bb65e687-db2b-4195-8471-6bddcdf63026", "scryfallIllustrationId": "b8114dec-882e-400c-8091-4eefda1204c5", "scryfallOracleId": "b3b4c21d-f8d7-455f-be46-d5eb909d54df", "subtypes": [], "supertypes": [], "text": "Search your library for a basic land card and put that card onto the battlefield. Then shuffle your library.", "type": "Sorcery", "types": ["Sorcery"], "uuid": "88db73ca-90c7-5fe8-a57f-59d519c7508c"}], "meta": {"date": "2019-11-10", "pricesDate": "2019-11-10", "version": "4.6.0+20191110"}, "name": "Zakk's First Deck", "releaseDate": "1996-06-10", "sideBoard": [], "type": "Intro Pack"}